<?xml version="1.0" encoding="UTF-8"?><!DOCTYPE tv SYSTEM "http://api.torrent-tv.ru/xmltv.dtd">
<tv generator-info-name="https://epg.shellykoral.com" generator-info-url="koral@shellykoral.com">
<channel id="CCTV5(4K)">
<display-name lang="zh">CCTV5(4K)</display-name>
</channel>
<programme start="20250526010800 +0800" stop="20250526023500 +0800" channel="CCTV5(4K)">
<title lang="zh">实况录像-2025年世界田联钻石联赛 厦门站</title><desc lang="zh"></desc>
</programme>
<programme start="20250526023500 +0800" stop="20250526040000 +0800" channel="CCTV5(4K)">
<title lang="zh">实况录像-2025年ATP1000男子网球大师赛 蒙特卡洛站 1/4决赛</title><desc lang="zh"></desc>
</programme>
<programme start="20250526040000 +0800" stop="20250526053000 +0800" channel="CCTV5(4K)">
<title lang="zh">国际足球赛场-24-25赛季法甲联赛第29轮 摩纳哥—马赛（4K）</title><desc lang="zh"></desc>
</programme>
<programme start="20250526053000 +0800" stop="20250526060000 +0800" channel="CCTV5(4K)">
<title lang="zh">赛事集锦-2025年三人篮球亚洲杯1（4K）</title><desc lang="zh"></desc>
</programme>
<programme start="20250526060000 +0800" stop="20250526063000 +0800" channel="CCTV5(4K)">
<title lang="zh">实况录像-2025年世界泳联花样游泳世界杯 加拿大站 1</title><desc lang="zh"></desc>
</programme>
<programme start="20250526063000 +0800" stop="20250526070000 +0800" channel="CCTV5(4K)">
<title lang="zh">健身动起来</title><desc lang="zh"></desc>
</programme>
<programme start="20250526070000 +0800" stop="20250526080000 +0800" channel="CCTV5(4K)">
<title lang="zh">体坛晨报</title><desc lang="zh"></desc>
</programme>
<programme start="20250526080000 +0800" stop="20250526110000 +0800" channel="CCTV5(4K)">
<title lang="zh">2024/2025赛季美国职业篮球联赛-东部决赛（尼克斯-步行者）第三场</title><desc lang="zh"></desc>
</programme>
<programme start="20250526110000 +0800" stop="20250526120000 +0800" channel="CCTV5(4K)">
<title lang="zh">实况录像（奥林匹克）-2025年亚洲举重锦标赛 男子102公斤级决赛（4K）</title><desc lang="zh"></desc>
</programme>
<programme start="20250526120000 +0800" stop="20250526130500 +0800" channel="CCTV5(4K)">
<title lang="zh">体坛快讯</title><desc lang="zh"></desc>
</programme>
<programme start="20250526130500 +0800" stop="20250526132800 +0800" channel="CCTV5(4K)">
<title lang="zh">艺术里的奥林匹克(4K)</title><desc lang="zh"></desc>
</programme>
<programme start="20250526132800 +0800" stop="20250526150000 +0800" channel="CCTV5(4K)">
<title lang="zh">实况录像-2025年法国网球公开赛 第一轮（录播）1</title><desc lang="zh"></desc>
</programme>
<programme start="20250526150000 +0800" stop="20250526160000 +0800" channel="CCTV5(4K)">
<title lang="zh">实况录像-2025年世界泳联跳水世界杯总决赛（北京） 1</title><desc lang="zh"></desc>
</programme>
<programme start="20250526160000 +0800" stop="20250526180000 +0800" channel="CCTV5(4K)">
<title lang="zh">运动一起赢</title><desc lang="zh"></desc>
</programme>
<programme start="20250526180000 +0800" stop="20250526190000 +0800" channel="CCTV5(4K)">
<title lang="zh">体育新闻</title><desc lang="zh"></desc>
</programme>
<programme start="20250526190000 +0800" stop="20250526200000 +0800" channel="CCTV5(4K)">
<title lang="zh">天下足球</title><desc lang="zh"></desc>
</programme>
<programme start="20250526200000 +0800" stop="20250526213000 +0800" channel="CCTV5(4K)">
<title lang="zh">实况录像-2025年世界田联钻石联赛  拉巴特站（录播）</title><desc lang="zh"></desc>
</programme>
<programme start="20250526213000 +0800" stop="20250526220000 +0800" channel="CCTV5(4K)">
<title lang="zh">体育世界</title><desc lang="zh"></desc>
</programme>
<programme start="20250526220000 +0800" stop="20250526235900 +0800" channel="CCTV5(4K)">
<title lang="zh">2025年法国网球公开赛-第1轮1</title><desc lang="zh"></desc>
</programme>
</tv>