<?xml version="1.0" encoding="UTF-8"?><!DOCTYPE tv SYSTEM "http://api.torrent-tv.ru/xmltv.dtd">
<tv generator-info-name="https://epg.shellykoral.com" generator-info-url="koral@shellykoral.com">
<channel id="CCTV5(4K)">
<display-name lang="zh">CCTV5(4K)</display-name>
</channel>
<programme start="20240620021500 +0800" stop="20240620051500 +0800" channel="CCTV5(4K)">
<title lang="zh">2024欧洲杯足球赛-小组赛A组（苏格兰队—瑞士队）</title><desc lang="zh"></desc>
</programme>
<programme start="20240620051500 +0800" stop="20240620053000 +0800" channel="CCTV5(4K)">
<title lang="zh">实况录像-2024年全国游泳冠军赛  10分钟版  4</title><desc lang="zh"></desc>
</programme>
<programme start="20240620053000 +0800" stop="20240620060000 +0800" channel="CCTV5(4K)">
<title lang="zh">赛事集锦-2024年国际体联艺术体操世界杯-巴库站25分钟版2</title><desc lang="zh"></desc>
</programme>
<programme start="20240620060000 +0800" stop="20240620063000 +0800" channel="CCTV5(4K)">
<title lang="zh">实况录像-2024年奥运会自由式小轮车资格赛 上海站 决赛</title><desc lang="zh"></desc>
</programme>
<programme start="20240620063000 +0800" stop="20240620070000 +0800" channel="CCTV5(4K)">
<title lang="zh">健身动起来</title><desc lang="zh"></desc>
</programme>
<programme start="20240620070000 +0800" stop="20240620090800 +0800" channel="CCTV5(4K)">
<title lang="zh">体坛晨报</title><desc lang="zh"></desc>
</programme>
<programme start="20240620090800 +0800" stop="20240620104000 +0800" channel="CCTV5(4K)">
<title lang="zh">实况录像-2024年世界田联钻石联赛  尤金站</title><desc lang="zh"></desc>
</programme>
<programme start="20240620104000 +0800" stop="20240620120000 +0800" channel="CCTV5(4K)">
<title lang="zh">实况录像-2024全国青少年U系列攀岩联赛（眉山站）</title><desc lang="zh"></desc>
</programme>
<programme start="20240620120000 +0800" stop="20240620123500 +0800" channel="CCTV5(4K)">
<title lang="zh">体坛快讯</title><desc lang="zh"></desc>
</programme>
<programme start="20240620123500 +0800" stop="20240620125800 +0800" channel="CCTV5(4K)">
<title lang="zh">艺术里的奥林匹克</title><desc lang="zh"></desc>
</programme>
<programme start="20240620125800 +0800" stop="20240620140000 +0800" channel="CCTV5(4K)">
<title lang="zh">2024年皮划艇激流回旋世界杯-德国站（4K）</title><desc lang="zh"></desc>
</programme>
<programme start="20240620140000 +0800" stop="20240620180000 +0800" channel="CCTV5(4K)">
<title lang="zh">2024欧洲杯足球赛报道-星耀金杯-6</title><desc lang="zh"></desc>
</programme>
<programme start="20240620180000 +0800" stop="20240620183500 +0800" channel="CCTV5(4K)">
<title lang="zh">体育新闻</title><desc lang="zh"></desc>
</programme>
<programme start="20240620183500 +0800" stop="20240620200000 +0800" channel="CCTV5(4K)">
<title lang="zh">2024欧洲杯足球赛报道-足球盛宴-7</title><desc lang="zh"></desc>
</programme>
<programme start="20240620200000 +0800" stop="20240620231500 +0800" channel="CCTV5(4K)">
<title lang="zh">2024欧洲杯足球赛-小组赛C组（斯洛文尼亚队—塞尔维亚队）</title><desc lang="zh"></desc>
</programme>
<programme start="20240620231500 +0800" stop="20240620235900 +0800" channel="CCTV5(4K)">
<title lang="zh">2024欧洲杯足球赛-小组赛C组（丹麦队—英格兰队）</title><desc lang="zh"></desc>
</programme>
</tv>